rest_framework_include_mixin/__init__.py
rest_framework_include_mixin/mixins.py
djangorestframework_include_mixin-0.4.dist-info/LICENSE
djangorestframework_include_mixin-0.4.dist-info/METADATA
djangorestframework_include_mixin-0.4.dist-info/WHEEL
djangorestframework_include_mixin-0.4.dist-info/top_level.txt
djangorestframework_include_mixin-0.4.dist-info/zip-safe
djangorestframework_include_mixin-0.4.dist-info/RECORD
